bestcaptchasolverapi3/bestcaptchasolverapi.py
bestcaptchasolverapi3-0.2.dist-info/LICENSE.md
bestcaptchasolverapi3-0.2.dist-info/METADATA
bestcaptchasolverapi3-0.2.dist-info/WHEEL
bestcaptchasolverapi3-0.2.dist-info/top_level.txt
bestcaptchasolverapi3-0.2.dist-info/RECORD
