Metadata-Version: 2.1
Name: bestcaptchasolverapi3
Version: 0.2
Summary: Bestcaptchasolver python3 API library
Home-page: https://github.com/bestcaptchasolver/bestcaptchasolver-python3
Author: BestCaptchaSolver
Author-email: bcsolver@gmail.com
License: UNKNOWN
Download-URL: https://github.com/bestcaptchasolver/bestcaptchasolver-python3
Keywords: bestcaptchasolver,captcha,bypasscaptcha,decaptcher,decaptcha,2captcha,deathbycaptcha,anticaptcha,bypass-recaptcha-v2,google-recaptcha-solver,recaptcha-v2-captcha-solver,captcha-services-for-recaptcha-v2,bypass-invisible-recaptcha,bypass-no-captcha-recaptcha,recaptcha-solver-python,recaptcha-bypass-script
Platform: UNKNOWN
